[
  {
    "label": "Berlin",
    "id": "Q64",
    "lat": 52.516666666,
    "lng": 13.383333333
  },
  {
    "label": "Munich",
    "id": "Q1726",
    "lat": 48.1375,
    "lng": 11.575
  },
  {
    "label": "Hamburg",
    "id": "Q1055",
    "lat": 53.55,
    "lng": 10.0
  },
  {
    "label": "Frankfurt",
    "id": "Q1794",
    "lat": 50.110555555,
    "lng": 8.682222222
  },
  {
    "label": "Cologne",
    "id": "Q365",
    "lat": 50.942222222,
    "lng": 6.957777777
  },
  {
    "label": "Stuttgart",
    "id": "Q1022",
    "lat": 48.7775,
    "lng": 9.18
  },
  {
    "label": "Dresden",
    "id": "Q1731",
    "lat": 51.0493286,
    "lng": 13.7381437
  },
  {
    "label": "D\u00fcsseldorf",
    "id": "Q1718",
    "lat": 51.225555555,
    "lng": 6.776666666
  },
  {
    "label": "Hanover",
    "id": "Q1715",
    "lat": 52.374444444,
    "lng": 9.738611111
  },
  {
    "label": "Leipzig",
    "id": "Q2079",
    "lat": 51.3406321,
    "lng": 12.3747329
  },
  {
    "label": "Bremen",
    "id": "Q24879",
    "lat": 53.075833333,
    "lng": 8.807222222
  },
  {
    "label": "Bonn",
    "id": "Q586",
    "lat": 50.735277777,
    "lng": 7.102222222
  },
  {
    "label": "Wiesbaden",
    "id": "Q1721",
    "lat": 50.0825,
    "lng": 8.24
  },
  {
    "label": "Nuremberg",
    "id": "Q2090",
    "lat": 49.453888888,
    "lng": 11.0775
  },
  {
    "label": "Dortmund",
    "id": "Q1295",
    "lat": 51.513888888,
    "lng": 7.465277777
  },
  {
    "label": "Mainz",
    "id": "Q1720",
    "lat": 49.999444444,
    "lng": 8.273611111
  },
  {
    "label": "Erfurt",
    "id": "Q1729",
    "lat": 50.978055555,
    "lng": 11.028888888
  },
  {
    "label": "Aachen",
    "id": "Q1017",
    "lat": 50.776207,
    "lng": 6.083788
  },
  {
    "label": "Kiel",
    "id": "Q1707",
    "lat": 54.323333333,
    "lng": 10.139444444
  },
  {
    "label": "Magdeburg",
    "id": "Q1733",
    "lat": 52.1315889,
    "lng": 11.6399609
  },
  {
    "label": "Essen",
    "id": "Q2066",
    "lat": 51.450833333,
    "lng": 7.013055555
  },
  {
    "label": "L\u00fcbeck",
    "id": "Q2843",
    "lat": 53.869722222,
    "lng": 10.686388888
  },
  {
    "label": "Karlsruhe",
    "id": "Q1040",
    "lat": 49.016666666,
    "lng": 8.4
  },
  {
    "label": "Bremen",
    "id": "Q1209",
    "lat": 53.133333333,
    "lng": 8.733333333
  },
  {
    "label": "Mannheim",
    "id": "Q2119",
    "lat": 49.487777777,
    "lng": 8.466111111
  },
  {
    "label": "Duisburg",
    "id": "Q2100",
    "lat": 51.432222222,
    "lng": 6.761111111
  },
  {
    "label": "Freiburg im Breisgau",
    "id": "Q2833",
    "lat": 47.995,
    "lng": 7.85
  },
  {
    "label": "M\u00fcnster",
    "id": "Q2742",
    "lat": 51.9625,
    "lng": 7.625555555
  },
  {
    "label": "Augsburg",
    "id": "Q2749",
    "lat": 48.368888888,
    "lng": 10.897777777
  },
  {
    "label": "Halle (Saale)",
    "id": "Q2814",
    "lat": 51.482777777,
    "lng": 11.969722222
  },
  {
    "label": "Chemnitz",
    "id": "Q2795",
    "lat": 50.833333333,
    "lng": 12.916666666
  },
  {
    "label": "Rostock",
    "id": "Q2861",
    "lat": 54.083333333,
    "lng": 12.133333333
  },
  {
    "label": "Kassel",
    "id": "Q2865",
    "lat": 51.315777777,
    "lng": 9.497916666
  },
  {
    "label": "Bielefeld",
    "id": "Q2112",
    "lat": 52.016666666,
    "lng": 8.533333333
  },
  {
    "label": "Brunswick",
    "id": "Q2773",
    "lat": 52.269166666,
    "lng": 10.521111111
  },
  {
    "label": "Wuppertal",
    "id": "Q2107",
    "lat": 51.266666666,
    "lng": 7.183333333
  },
  {
    "label": "Gelsenkirchen",
    "id": "Q2765",
    "lat": 51.516666666,
    "lng": 7.1
  },
  {
    "label": "Bochum",
    "id": "Q2103",
    "lat": 51.483333333,
    "lng": 7.216666666
  },
  {
    "label": "M\u00f6nchengladbach",
    "id": "Q2758",
    "lat": 51.2,
    "lng": 6.433333333
  },
  {
    "label": "Krefeld",
    "id": "Q2805",
    "lat": 51.333333333,
    "lng": 6.566666666
  },
  {
    "label": "Oberhausen",
    "id": "Q2838",
    "lat": 51.4699,
    "lng": 6.8514
  }
]